l5x/__init__.py
l5x/dom.py
l5x/module.py
l5x/project.py
l5x/tag.py
tests/__init__.py
tests/fixture.py
tests/test_controller.py
tests/test_dom.py
tests/test_module.py
tests/test_programs.py
tests/test_project.py
tests/test_tags.py
l5x-1.6.dist-info/LICENSE.txt
l5x-1.6.dist-info/METADATA
l5x-1.6.dist-info/WHEEL
l5x-1.6.dist-info/top_level.txt
l5x-1.6.dist-info/RECORD
