Metadata-Version: 2.1
Name: l5x
Version: 1.6
Summary: RSLogix .L5X interface.
Home-page: https://github.com/jvalenzuela/l5x
Author: Jason Valenzuela
Author-email: jvalenzuela1977@gmail.com
License: LICENSE.txt
Classifier: Development Status :: 5 - Production/Stable
Classifier: License :: OSI Approved :: GNU General Public License v3 or later (GPLv3+)
Classifier: Intended Audience :: Developers
Classifier: Operating System :: OS Independent
Classifier: Programming Language :: Python :: 2.7
Classifier: Programming Language :: Python :: 3
Classifier: Topic :: Text Processing :: Markup :: XML
Classifier: Topic :: Software Development :: Libraries :: Python Modules
Classifier: Topic :: Scientific/Engineering :: Interface Engine/Protocol Translator
License-File: LICENSE.txt
